pycolmap/__init__.py
pycolmap/_core.cpython-311-x86_64-linux-gnu.so
pycolmap/py.typed
pycolmap/utils.py
pycolmap/_core/__init__.pyi
pycolmap/_core/cost_functions.pyi
pycolmap/_core/pyceres.pyi
pycolmap/cost_functions/__init__.py
pycolmap_cuda12.libs/libGLX-225e03fe.so.0.0.0
pycolmap_cuda12.libs/libGLdispatch-a0d0eb9f.so.0.0.0
pycolmap_cuda12.libs/libOpenGL-68996860.so.0.0.0
pycolmap_cuda12.libs/libgfortran-58726230.so.5.0.0
pycolmap_cuda12.libs/libgomp-14f972ab.so.1.0.0
pycolmap_cuda12.libs/libquadmath-a92b999f.so.0.0.0
pycolmap_cuda12-3.13.0.dist-info/METADATA
pycolmap_cuda12-3.13.0.dist-info/WHEEL
pycolmap_cuda12-3.13.0.dist-info/RECORD
pycolmap_cuda12-3.13.0.dist-info/licenses/COPYING.txt
